<Properties StartupConfiguration="{8712A8F9-CB01-41F6-9098-DE47070AD62E}|Default">
  <MonoDevelop.Ide.ItemProperties.MyMap.Android AndroidDesignerPreferredTheme="Theme.AppCompat.Light.NoActionBar" PreferredExecutionTarget="Android.Phone_Pixel_O" />
  <MonoDevelop.Ide.ItemProperties.MyMap.iOS FirstBuild="True" />
  <MonoDevelop.Ide.Workbench ActiveDocument="MyMap/MainPage.xaml.cs">
    <Files>
      <File FileName="MyMap/MainPage.xaml.cs" Line="34" Column="42" />
      <File FileName="MyMap.Android/MainActivity.cs" Line="26" Column="19" />
      <File FileName="MyMap/App.xaml.cs" Line="13" Column="33" />
      <File FileName="MyMap/MainPage.xaml" Line="38" Column="24" />
    </Files>
    <Pads>
      <Pad Id="ProjectPad">
        <State name="__root__">
          <Node name="MyMap" expanded="True">
            <Node name="MyMap" expanded="True">
              <Node name="Dependencies" expanded="True">
                <Node name="PackageDependencies" expanded="True" />
              </Node>
              <Node name="App.xaml" expanded="True" />
              <Node name="MainPage.xaml" expanded="True">
                <Node name="MainPage.xaml.cs" selected="True" />
              </Node>
            </Node>
            <Node name="MyMap.Android" expanded="True">
              <Node name="Assets" expanded="True" />
            </Node>
          </Node>
        </State>
      </Pad>
    </Pads>
  </MonoDevelop.Ide.Workbench>
  <MonoDevelop.Ide.DebuggingService.PinnedWatches />
  <MonoDevelop.Ide.Workspace ActiveConfiguration="Debug" />
  <MonoDevelop.Ide.DebuggingService.Breakpoints>
    <BreakpointStore />
  </MonoDevelop.Ide.DebuggingService.Breakpoints>
  <MultiItemStartupConfigurations />
</Properties>